README
setup.py
eve_ng_sdk.egg-info/PKG-INFO
eve_ng_sdk.egg-info/SOURCES.txt
eve_ng_sdk.egg-info/dependency_links.txt
eve_ng_sdk.egg-info/requires.txt
eve_ng_sdk.egg-info/top_level.txt
resteve/__init__.py
resteve/device.py
resteve/eve.py
resteve/helper.py
resteve/server.py
samples/__init__.py
samples/app-1.py
samples/app-2.py
samples/get_users.py