Metadata-Version: 1.1
Name: eve-ng-sdk
Version: 0.0.15
Summary: EVE-NG REST API Library
Home-page: https://github.com/slarimore02/eve-ng-python-sdk.git
Author: Sean Larimore
Author-email: UNKNOWN
License: MIT
Keywords: eve-ng unetlab rest api sdk library client
Platform: UNKNOWN
Classifier: Development Status :: 3 - Alpha
Classifier: Programming Language :: Python :: 2.7
